.flake8
.gitignore
.gitmodules
.isort.cfg
.pre-commit-config.yaml
BUILD_TIMELORD.md
CHANGELOG.md
CODE_OF_CONDUCT.md
CONTRIBUTING.md
INSTALL.md
Install-gui.ps1
Install.ps1
LICENSE
README.md
azure-pipelines.yml
install-gui.sh
install-timelord.sh
install.sh
installhelper.py
mypy.ini
pecanroll-spinning-128.gif
pyproject.toml
run-py-tests.sh
setup.py
.github/FUNDING.yml
.github/dependabot.yml
.github/ISSUE_TEMPLATE/bug_report.md
.github/ISSUE_TEMPLATE/config.yml
.github/linters/.flake8
.github/linters/.isort.cfg
.github/linters/.markdown-lint.yml
.github/linters/.python-black
.github/linters/.python-lint
.github/workflows/build-linux-installer-deb.yml
.github/workflows/build-linux-installer-rpm.yml
.github/workflows/build-macos-installer.yml
.github/workflows/build-windows-installer.yml
.github/workflows/codeql-analysis.yml
.github/workflows/mozilla-ca-cert.yml
.github/workflows/test-install-scripts.yml
benchmarks/coin_store.py
build_scripts/build_linux_deb.sh
build_scripts/build_linux_rpm.sh
build_scripts/build_macos.sh
build_scripts/build_macos_m1.sh
build_scripts/build_windows.ps1
build_scripts/clean-runner.sh
build_scripts/installer-version.py
mozilla-ca/.gitignore
mozilla-ca/LICENSE
mozilla-ca/__init__.py
mozilla-ca/cacert.pem
mozilla-ca/.github/workflows/update-cert.yaml
rolls/__init__.py
rolls/py.typed
rolls/pyinstaller.spec
rolls-blockchain-gui/.editorconfig
rolls-blockchain-gui/.env
rolls-blockchain-gui/.env.example
rolls-blockchain-gui/.eslintignore
rolls-blockchain-gui/.eslintrc.js
rolls-blockchain-gui/.gitignore
rolls-blockchain-gui/.linguirc
rolls-blockchain-gui/.prettierrc.js
rolls-blockchain-gui/CODE_OF_CONDUCT.md
rolls-blockchain-gui/CONTRIBUTING.md
rolls-blockchain-gui/LICENSE
rolls-blockchain-gui/README.md
rolls-blockchain-gui/babel.config.js
rolls-blockchain-gui/crowdin.yml
rolls-blockchain-gui/entitlements.mac.plist
rolls-blockchain-gui/hddcoinblockchain.provisionprofile
rolls-blockchain-gui/package-lock.json
rolls-blockchain-gui/package.json
rolls_blockchain.egg-info/PKG-INFO
rolls_blockchain.egg-info/SOURCES.txt
rolls_blockchain.egg-info/dependency_links.txt
rolls_blockchain.egg-info/entry_points.txt
rolls_blockchain.egg-info/not-zip-safe
rolls_blockchain.egg-info/requires.txt
rolls_blockchain.egg-info/top_level.txt
