Metadata-Version: 2.1
Name: rolls-blockchain
Version: 1.3a1.dev5
Summary: PecanRolls blockchain full node, farmer, timelord, and wallet.
Home-page: https://pecanrolls.net/
Author: nickhenry.eth
Author-email: nick.henryhousehold@gmail.com
License: Apache License
Keywords: rolls blockchain node
Platform: UNKNOWN
Requires-Python: >=3.7, <4
Provides-Extra: uvloop
Provides-Extra: dev
Provides-Extra: upnp
License-File: LICENSE
